[{"Date":"09/02/2022","Open":2.52,"High":2.55,"Low":2.42,"Close":2.45,"Volume":74493.0},{"Date":"09/01/2022","Open":2.52,"High":2.63,"Low":2.45,"Close":2.6,"Volume":72341.0},{"Date":"08/31/2022","Open":2.6,"High":2.8,"Low":2.42,"Close":2.65,"Volume":184553.0},{"Date":"08/30/2022","Open":2.71,"High":2.92,"Low":2.5,"Close":2.55,"Volume":739388.0},{"Date":"08/29/2022","Open":2.69,"High":2.7899,"Low":2.63,"Close":2.68,"Volume":39897.0},{"Date":"08/26/2022","Open":3.182,"High":3.32,"Low":2.33,"Close":2.6,"Volume":372912.0},{"Date":"08/25/2022","Open":3.3,"High":3.4,"Low":3.1102,"Close":3.23,"Volume":67491.0},{"Date":"08/24/2022","Open":3.12,"High":3.3,"Low":3.05,"Close":3.23,"Volume":76562.0},{"Date":"08/23/2022","Open":3.1,"High":3.12,"Low":3.02,"Close":3.12,"Volume":56811.0},{"Date":"08/22/2022","Open":3.23,"High":3.47,"Low":3.08,"Close":3.13,"Volume":182443.0},{"Date":"08/19/2022","Open":3.47,"High":3.47,"Low":3.27,"Close":3.37,"Volume":25063.0},{"Date":"08/18/2022","Open":3.53,"High":3.53,"Low":3.25,"Close":3.43,"Volume":46526.0},{"Date":"08/17/2022","Open":3.63,"High":3.66,"Low":3.45,"Close":3.53,"Volume":28674.0},{"Date":"08/16/2022","Open":3.75,"High":3.76,"Low":3.5014,"Close":3.62,"Volume":50147.0},{"Date":"08/15/2022","Open":3.77,"High":3.7899,"Low":3.5176,"Close":3.6,"Volume":106412.0},{"Date":"08/12/2022","Open":3.88,"High":3.96,"Low":3.6,"Close":3.73,"Volume":119621.0},{"Date":"08/11/2022","Open":3.68,"High":4.33,"Low":3.42,"Close":3.95,"Volume":816350.0},{"Date":"08/10/2022","Open":3.72,"High":3.8099,"Low":3.6,"Close":3.6927,"Volume":69305.0},{"Date":"08/09/2022","Open":3.71,"High":3.85,"Low":3.56,"Close":3.74,"Volume":146090.0},{"Date":"08/08/2022","Open":3.78,"High":3.89,"Low":3.62,"Close":3.81,"Volume":200237.0},{"Date":"08/05/2022","Open":3.46,"High":3.73,"Low":3.3,"Close":3.61,"Volume":284622.0},{"Date":"08/04/2022","Open":3.19,"High":3.5533,"Low":3.11,"Close":3.43,"Volume":544464.0},{"Date":"08/03/2022","Open":2.85,"High":3.65,"Low":2.75,"Close":3.24,"Volume":1836999.0},{"Date":"08/02/2022","Open":2.7,"High":2.9,"Low":2.68,"Close":2.8423,"Volume":258132.0},{"Date":"08/01/2022","Open":2.71,"High":2.93,"Low":2.7,"Close":2.74,"Volume":376982.0},{"Date":"07/29/2022","Open":2.86,"High":2.9,"Low":2.7,"Close":2.78,"Volume":287335.0},{"Date":"07/28/2022","Open":2.7,"High":3.19,"Low":2.64,"Close":2.88,"Volume":695588.0},{"Date":"07/27/2022","Open":2.64,"High":2.72,"Low":2.54,"Close":2.7,"Volume":111211.0},{"Date":"07/26/2022","Open":2.72,"High":2.75,"Low":2.62,"Close":2.65,"Volume":81429.0},{"Date":"07/25/2022","Open":2.78,"High":2.8583,"Low":2.68,"Close":2.75,"Volume":101051.0},{"Date":"07/22/2022","Open":2.88,"High":2.9662,"Low":2.72,"Close":2.78,"Volume":177087.0},{"Date":"07/21/2022","Open":2.89,"High":3.1981,"Low":2.82,"Close":2.87,"Volume":380358.0},{"Date":"07/20/2022","Open":3.12,"High":3.13,"Low":2.86,"Close":2.87,"Volume":124624.0},{"Date":"07/19/2022","Open":2.93,"High":3.14,"Low":2.86,"Close":3.14,"Volume":239855.0},{"Date":"07/18/2022","Open":2.79,"High":2.9471,"Low":2.77,"Close":2.89,"Volume":124676.0},{"Date":"07/15/2022","Open":3.04,"High":3.0899,"Low":2.7,"Close":2.77,"Volume":277247.0},{"Date":"07/14/2022","Open":3.04,"High":3.16,"Low":3.01,"Close":3.03,"Volume":164146.0},{"Date":"07/13/2022","Open":3.09,"High":3.15,"Low":3.0,"Close":3.03,"Volume":157344.0},{"Date":"07/12/2022","Open":3.11,"High":3.2789,"Low":3.08,"Close":3.1,"Volume":142698.0},{"Date":"07/11/2022","Open":3.6,"High":3.6,"Low":3.105,"Close":3.12,"Volume":276730.0},{"Date":"07/08/2022","Open":3.33,"High":3.67,"Low":3.28,"Close":3.52,"Volume":400435.0},{"Date":"07/07/2022","Open":3.66,"High":3.7701,"Low":3.26,"Close":3.29,"Volume":347958.0},{"Date":"07/06/2022","Open":3.65,"High":3.97,"Low":3.65,"Close":3.7,"Volume":327368.0},{"Date":"07/05/2022","Open":4.55,"High":4.67,"Low":3.4787,"Close":3.61,"Volume":866943.0},{"Date":"07/01/2022","Open":4.78,"High":5.06,"Low":4.55,"Close":4.65,"Volume":291032.0},{"Date":"06/30/2022","Open":4.51,"High":5.22,"Low":4.4,"Close":4.74,"Volume":868764.0},{"Date":"06/29/2022","Open":5.09,"High":5.09,"Low":4.55,"Close":4.66,"Volume":243098.0},{"Date":"06/28/2022","Open":6.22,"High":6.3,"Low":4.91,"Close":5.0,"Volume":741015.0},{"Date":"06/27/2022","Open":6.07,"High":7.04,"Low":5.8423,"Close":6.69,"Volume":2093783.0},{"Date":"06/24/2022","Open":5.72,"High":6.4393,"Low":5.51,"Close":6.14,"Volume":3601546.0},{"Date":"06/23/2022","Open":7.55,"High":8.5,"Low":6.29,"Close":6.64,"Volume":55163969.0},{"Date":"06/22/2022","Open":3.51,"High":8.4,"Low":3.45,"Close":5.83,"Volume":57066898.0},{"Date":"06/21/2022","Open":3.34,"High":3.44,"Low":3.2756,"Close":3.42,"Volume":97343.0},{"Date":"06/17/2022","Open":3.15,"High":3.35,"Low":3.1101,"Close":3.35,"Volume":62738.0},{"Date":"06/16/2022","Open":3.07,"High":3.1698,"Low":3.05,"Close":3.16,"Volume":88737.0},{"Date":"06/15/2022","Open":3.29,"High":3.29,"Low":3.03,"Close":3.07,"Volume":200967.0},{"Date":"06/14/2022","Open":3.11,"High":3.21,"Low":3.0,"Close":3.03,"Volume":90871.0},{"Date":"06/13/2022","Open":3.1,"High":3.19,"Low":2.9,"Close":3.11,"Volume":137481.0},{"Date":"06/10/2022","Open":3.12,"High":3.42,"Low":3.1,"Close":3.22,"Volume":298891.0},{"Date":"06/09/2022","Open":3.9,"High":3.95,"Low":3.35,"Close":3.36,"Volume":662992.0},{"Date":"06/08/2022","Open":6.5,"High":6.5,"Low":4.01,"Close":4.06,"Volume":1920116.0}]